[
{"name": "BTC"},
{"name": "ETH"},
{"name": "USDT"},
{"name": "BNB"},
{"name": "XRP"},
{"name": "USDC"},
{"name": "SOL"},
{"name": "ADA"},
{"name": "DOGE"},
{"name": "TRX"},
{"name": "TON"},
{"name": "DAI"},
{"name": "MATIC"},
{"name": "DOT"},
{"name": "LTC"},
{"name": "BCH"},
{"name": "WBTC"},
{"name": "SHIB"},
{"name": "LINK"},
{"name": "TUSD"},
{"name": "LEO"},
{"name": "AVAX"},
{"name": "XLM"},
{"name": "XMR"},
{"name": "ATOM"},
{"name": "UNI"},
{"name": "OKB"},
{"name": "ETC"},
{"name": "BUSD"},
{"name": "HBAR"},
{"name": "FIL"},
{"name": "LDO"},
{"name": "ICP"},
{"name": "MKR"},
{"name": "MNT"},
{"name": "APT"},
{"name": "CRO"},
{"name": "VET"},
{"name": "ARB"},
{"name": "OP"},
{"name": "NEAR"},
{"name": "QNT"},
{"name": "AAVE"},
{"name": "GRT"},
{"name": "ALGO"},
{"name": "BSV"},
{"name": "STX"},
{"name": "USDD"},
{"name": "XDC"},
{"name": "RUNE"},
{"name": "IMX"},
{"name": "XTZ"},
{"name": "AXS"},
{"name": "EOS"},
{"name": "EGLD"},
{"name": "SAND"},
{"name": "THETA"},
{"name": "BGB"},
{"name": "INJ"},
{"name": "RNDR"},
{"name": "MANA"},
{"name": "SNX"},
{"name": "FTM"},
{"name": "XEC"},
{"name": "KAVA"},
{"name": "NEO"},
{"name": "USDP"},
{"name": "FLOW"},
{"name": "CHZ"},
{"name": "PAXG"},
{"name": "XAUt"},
{"name": "KCS"},
{"name": "ZEC"},
{"name": "APE"},
{"name": "CRV"},
{"name": "RPL"},
{"name": "CFX"},
{"name": "MIOTA"},
{"name": "SUI"},
{"name": "FXS"},
{"name": "HT"},
{"name": "MINA"},
{"name": "DYDX"},
{"name": "KLAY"},
{"name": "COMP"},
{"name": "CSPR"},
{"name": "BTT"},
{"name": "GALA"},
{"name": null},
{"name": null},
{"name": null},
{"name": null},
{"name": "NFT"},
{"name": "DASH"},
{"name": "NEXO"},
{"name": "WOO"},
{"name": "PEPE"},
{"name": "AR"},
{"name": "1INCH"},
{"name": "ZIL"}
]